<?xml version="1.0" encoding="utf-8" ?><dwsync><file name="bald-eagle.jpg" server="www.ingledow.co.uk" local="3348864000" remote="16233765888" /><file name="banner.jpg" server="www.ingledow.co.uk" local="3346617600" remote="16231519488" /><file name="banner3.jpg" server="www.ingledow.co.uk" local="3346617600" remote="16231519488" /><file name="blog-sep.jpg" server="www.ingledow.co.uk" local="3346617600" remote="16231519488" /><file name="clear.gif" server="www.ingledow.co.uk" local="3348518400" remote="16233420288" /><file name="close.jpg" server="www.ingledow.co.uk" local="3346617600" remote="16231519488" /><file name="facebook-rollover.png" server="www.ingledow.co.uk" local="3346617600" remote="16231519488" /><file name="facebook.png" server="www.ingledow.co.uk" local="3346617600" remote="16231519488" /><file name="follow.png" server="www.ingledow.co.uk" local="3346617600" remote="16231519488" /><file name="followhover.png" server="www.ingledow.co.uk" local="3346617600" remote="16231519488" /><file name="footer-shadow.jpg" server="www.ingledow.co.uk" local="3346617600" remote="16231519488" /><file name="id-dev.png" server="www.ingledow.co.uk" local="3346790400" remote="16231692288" /><file name="logo.png" server="www.ingledow.co.uk" local="3347654400" remote="16232556288" /><file name="Logodes.jpg" server="www.ingledow.co.uk" local="3346617600" remote="16231519488" /><file name="macaw.jpg" server="www.ingledow.co.uk" local="3348864000" remote="16233765888" /><file name="mboaden.jpg" server="www.ingledow.co.uk" local="3355686000" remote="16240587888" /><file name="new banner.psd" server="www.ingledow.co.uk" local="3346617600" remote="16231519488" /><file name="new small banner.psd" server="www.ingledow.co.uk" local="3346617600" remote="16231519488" /><file name="panda.jpg" server="www.ingledow.co.uk" local="3348864000" remote="16233765888" /><file name="quote.jpg" server="www.ingledow.co.uk" local="3346617600" remote="16231519488" /><file name="quote.png" server="www.ingledow.co.uk" local="3346617600" remote="16231519488" /><file name="quotehover.png" server="www.ingledow.co.uk" local="3346617600" remote="16231519488" /><file name="rss-feed-rollover.png" server="www.ingledow.co.uk" local="3346617600" remote="16231519488" /><file name="rss-feed.png" server="www.ingledow.co.uk" local="3346617600" remote="16231519488" /><file name="send-rollover.png" server="www.ingledow.co.uk" local="3346617600" remote="16231519488" /><file name="send.png" server="www.ingledow.co.uk" local="3346617600" remote="16231519488" /><file name="share-facebook-rollover.png" server="www.ingledow.co.uk" local="3346963200" remote="16231865088" /><file name="share-facebook.png" server="www.ingledow.co.uk" local="3346963200" remote="16231865088" /><file name="share-stumble-rollover.png" server="www.ingledow.co.uk" local="3346963200" remote="16231865088" /><file name="share-stumble.png" server="www.ingledow.co.uk" local="3346963200" remote="16231865088" /><file name="share-twitter-rollover.png" server="www.ingledow.co.uk" local="3346963200" remote="16231865088" /><file name="share-twitter.png" server="www.ingledow.co.uk" local="3346963200" remote="16231865088" /><file name="small-banner old.jpg" server="www.ingledow.co.uk" local="3346617600" remote="16231519488" /><file name="small-banner.jpg" server="www.ingledow.co.uk" local="3346617600" remote="16231519488" /><file name="social-media.png" server="www.ingledow.co.uk" local="3346790400" remote="16231692288" /><file name="tiger.jpg" server="www.ingledow.co.uk" local="3348864000" remote="16233765888" /><file name="twitter-rollover.png" server="www.ingledow.co.uk" local="3346617600" remote="16231519488" /><file name="twitter.png" server="www.ingledow.co.uk" local="3346617600" remote="16231519488" /><file name="VALIDcss-rollover.png" server="www.ingledow.co.uk" local="3346963200" remote="16231865088" /><file name="VALIDcss.png" server="www.ingledow.co.uk" local="3346963200" remote="16231865088" /><file name="validhome.png" server="www.ingledow.co.uk" local="3346790400" remote="16231692288" /><file name="VALIDhtml-rollover.png" server="www.ingledow.co.uk" local="3346963200" remote="16231865088" /><file name="VALIDhtml.png" server="www.ingledow.co.uk" local="3346963200" remote="16231865088" /><file name="wdesign.jpg" server="www.ingledow.co.uk" local="3346790400" remote="16231692288" /><file name="wordpress-logo.png" server="www.ingledow.co.uk" local="3346790400" remote="16231692288" /><file name="youtube-rollover.png" server="www.ingledow.co.uk" local="3346617600" remote="16231519488" /><file name="youtube.png" server="www.ingledow.co.uk" local="3346617600" remote="16231519488" /></dwsync>